miguel_lib-0.2.3.dist-info/METADATA
miguel_lib-0.2.3.dist-info/WHEEL
miguel_lib-0.2.3.dist-info/license_files/LICENSE
miguel_lib/__init__.py
miguel_lib/__init__.pyi
miguel_lib/py.typed
miguel_lib/miguel_lib.pyd
miguel_lib-0.2.3.dist-info/RECORD
