Metadata-Version: 2.1
Name: miguel_lib
Version: 0.2.3
Classifier: Development Status :: 4 - Beta
Classifier: License :: OSI Approved :: GNU Lesser General Public License v2 or later (LGPLv2+)
Classifier: Operating System :: POSIX :: Linux
Classifier: Operating System :: MacOS
Classifier: Operating System :: Microsoft :: Windows
Classifier: Programming Language :: Rust
Classifier: Programming Language :: Python :: Implementation :: CPython
Classifier: Programming Language :: Python :: Implementation :: PyPy
Classifier: Programming Language :: Python :: 3.7
Classifier: Programming Language :: Python :: 3.8
Classifier: Programming Language :: Python :: 3.9
Classifier: Programming Language :: Python :: 3.10
Classifier: Programming Language :: Python :: 3.11
Classifier: Programming Language :: Python :: 3 :: Only
License-File: LICENSE
Summary: Random crap I like to use
Author: MiguelX413
Author-email: lbpgaming27@gmail.com
Requires-Python: >=3.7
Project-URL: GitHub, https://github.com/MiguelX413/miguel_lib
Project-URL: GitLab, https://gitlab.com/MiguelX413/miguel_lib
